monome.py
pymonome-0.10.0.dist-info/DESCRIPTION.rst
pymonome-0.10.0.dist-info/METADATA
pymonome-0.10.0.dist-info/RECORD
pymonome-0.10.0.dist-info/WHEEL
pymonome-0.10.0.dist-info/metadata.json
pymonome-0.10.0.dist-info/top_level.txt
