Metadata-Version: 2.0
Name: pymonome
Version: 0.10.0
Summary: a monome serialosc client in python
Home-page: https://github.com/artfwo/pymonome
Author: Artem Popov
Author-email: artfwo@gmail.com
License: MIT
Platform: UNKNOWN
Classifier: Development Status :: 4 - Beta
Classifier: Intended Audience :: Developers
Classifier: License :: OSI Approved :: MIT License
Classifier: Programming Language :: Python :: 3
Classifier: Topic :: Multimedia :: Sound/Audio
Classifier: Topic :: Software Development :: Libraries
Requires-Dist: aiosc
